{"scenes": [{"objects": [{"color": "purple", "size": "large", "rotation": 0.0, "pixel_coords": [109, 126, 11.139153480529785], "3d_coords": [-2.0, -1.940000057220459, 0.699999988079071], "material": "metal", "shape": "cube"}, {"color": "brown", "size": "large", "rotation": 0.0, "pixel_coords": [168, 160, 9.80388069152832], "3d_coords": [0.07999999821186066, -1.8600000143051147, 0.699999988079071], "material": "rubber", "shape": "sphere"}, {"color": "purple", "size": "large", "rotation": 0.0, "pixel_coords": [247, 127, 11.078664779663086], "3d_coords": [-0.029999999329447746, 0.2199999988079071, 0.699999988079071], "material": "metal", "shape": "cube"}, {"color": "brown", "size": "large", "rotation": 0.0, "pixel_coords": [319, 162, 9.725467681884766], "3d_coords": [1.9900000095367432, 0.20000000298023224, 0.699999988079071], "material": "rubber", "shape": "sphere"}], "image_filename": "CLEVR_shield-fovariant-13_000000.png", "split": "shield-fovariant-13", "image_index": 0, "directions": {"above": [0.0, 0.0, 1.0], "below": [-0.0, -0.0, -1.0], "right": [0.6563112735748291, 0.7544902563095093, -0.0], "left": [-0.6563112735748291, -0.7544902563095093, 0.0], "front": [0.754490315914154, -0.6563112735748291, -0.0], "behind": [-0.754490315914154, 0.6563112735748291, 0.0]}, "relationships": {"left": [[], [0], [0, 1], [0, 1, 2]], "front": [[1, 3], [], [1, 3], []], "behind": [[], [0, 2], [], [0, 2]], "right": [[1, 2, 3], [2, 3], [3], []]}}, {"objects": [{"color": "brown", "size": "large", "rotation": 0.0, "pixel_coords": [105, 126, 11.125277519226074], "3d_coords": [-2.0399999618530273, -2.009999990463257, 0.699999988079071], "material": "rubber", "shape": "sphere"}, {"color": "purple", "size": "large", "rotation": 0.0, "pixel_coords": [153, 161, 9.75156307220459], "3d_coords": [-0.05000000074505806, -2.0999999046325684, 0.699999988079071], "material": "metal", "shape": "cube"}, {"color": "brown", "size": "large", "rotation": 0.0, "pixel_coords": [237, 129, 10.972349166870117], "3d_coords": [-0.07000000029802322, -0.009999999776482582, 0.699999988079071], "material": "rubber", "shape": "sphere"}, {"color": "purple", "size": "large", "rotation": 0.0, "pixel_coords": [311, 166, 9.585942268371582], "3d_coords": [2.0, -0.029999999329447746, 0.699999988079071], "material": "metal", "shape": "cube"}], "image_filename": "CLEVR_shield-fovariant-13_000001.png", "split": "shield-fovariant-13", "image_index": 1, "directions": {"above": [0.0, 0.0, 1.0], "below": [-0.0, -0.0, -1.0], "right": [0.6563112735748291, 0.7544902563095093, -0.0], "left": [-0.6563112735748291, -0.7544902563095093, 0.0], "front": [0.754490315914154, -0.6563112735748291, -0.0], "behind": [-0.754490315914154, 0.6563112735748291, 0.0]}, "relationships": {"left": [[], [0], [0, 1], [0, 1, 2]], "front": [[1, 3], [], [1, 3], []], "behind": [[], [0, 2], [], [0, 2]], "right": [[1, 2, 3], [2, 3], [3], []]}}, {"objects": [{"color": "purple", "size": "large", "rotation": 0.0, "pixel_coords": [106, 130, 10.959505081176758], "3d_coords": [-1.8600000143051147, -2.0899999141693115, 0.699999988079071], "material": "metal", "shape": "cube"}, {"color": "brown", "size": "large", "rotation": 0.0, "pixel_coords": [156, 161, 9.741464614868164], "3d_coords": [0.0, -2.059999942779541, 0.699999988079071], "material": "rubber", "shape": "sphere"}, {"color": "purple", "size": "large", "rotation": 0.0, "pixel_coords": [239, 134, 10.783466339111328], "3d_coords": [0.10999999940395355, -0.12999999523162842, 0.699999988079071], "material": "metal", "shape": "cube"}], "image_filename": "CLEVR_shield-fovariant-13_000002.png", "split": "shield-fovariant-13", "image_index": 2, "directions": {"above": [0.0, 0.0, 1.0], "below": [-0.0, -0.0, -1.0], "right": [0.6563112735748291, 0.7544902563095093, -0.0], "left": [-0.6563112735748291, -0.7544902563095093, 0.0], "front": [0.754490315914154, -0.6563112735748291, -0.0], "behind": [-0.754490315914154, 0.6563112735748291, 0.0]}, "relationships": {"left": [[], [0], [0, 1]], "front": [[1], [], [1]], "behind": [[], [0, 2], []], "right": [[1, 2], [2], []]}}, {"objects": [{"color": "yellow", "size": "small", "rotation": 0.0, "pixel_coords": [48, 139, 11.352639198303223], "3d_coords": [-2.950000047683716, -2.950000047683716, 0.3499999940395355], "material": "metal", "shape": "cube"}, {"color": "red", "size": "small", "rotation": 0.0, "pixel_coords": [67, 155, 10.728310585021973], "3d_coords": [-2.009999990463257, -2.950000047683716, 0.3499999940395355], "material": "rubber", "shape": "sphere"}, {"color": "yellow", "size": "small", "rotation": 0.0, "pixel_coords": [110, 142, 11.255520820617676], "3d_coords": [-1.9600000381469727, -1.9800000190734863, 0.3499999940395355], "material": "metal", "shape": "cube"}, {"color": "red", "size": "small", "rotation": 0.0, "pixel_coords": [132, 159, 10.575737953186035], "3d_coords": [-0.9800000190734863, -2.0299999713897705, 0.3499999940395355], "material": "rubber", "shape": "sphere"}, {"color": "yellow", "size": "small", "rotation": 0.0, "pixel_coords": [171, 145, 11.106405258178711], "3d_coords": [-0.9700000286102295, -1.100000023841858, 0.3499999940395355], "material": "metal", "shape": "cube"}, {"color": "red", "size": "small", "rotation": 0.0, "pixel_coords": [205, 160, 10.541308403015137], "3d_coords": [0.019999999552965164, -0.9399999976158142, 0.3499999940395355], "material": "rubber", "shape": "sphere"}, {"color": "green", "size": "small", "rotation": 0.0, "pixel_coords": [240, 145, 11.116739273071289], "3d_coords": [-0.019999999552965164, 0.009999999776482582, 0.3499999940395355], "material": "metal", "shape": "cube"}, {"color": "red", "size": "small", "rotation": 0.0, "pixel_coords": [276, 162, 10.442461967468262], "3d_coords": [1.0299999713897705, 0.05000000074505806, 0.3499999940395355], "material": "rubber", "shape": "sphere"}, {"color": "green", "size": "small", "rotation": 0.0, "pixel_coords": [309, 148, 10.984683990478516], "3d_coords": [1.0399999618530273, 1.0, 0.3499999940395355], "material": "metal", "shape": "cube"}, {"color": "red", "size": "small", "rotation": 0.0, "pixel_coords": [345, 167, 10.285840034484863], "3d_coords": [2.0399999618530273, 0.9399999976158142, 0.3499999940395355], "material": "rubber", "shape": "sphere"}, {"color": "green", "size": "small", "rotation": 0.0, "pixel_coords": [375, 149, 10.949663162231445], "3d_coords": [1.9800000190734863, 2.0199999809265137, 0.3499999940395355], "material": "metal", "shape": "cube"}, {"color": "red", "size": "small", "rotation": 0.0, "pixel_coords": [415, 167, 10.276521682739258], "3d_coords": [2.950000047683716, 1.9700000286102295, 0.3499999940395355], "material": "rubber", "shape": "sphere"}], "image_filename": "CLEVR_shield-fovariant-13_000003.png", "split": "shield-fovariant-13", "image_index": 3, "directions": {"above": [0.0, 0.0, 1.0], "below": [-0.0, -0.0, -1.0], "right": [0.6563112735748291, 0.7544902563095093, -0.0], "left": [-0.6563112735748291, -0.7544902563095093, 0.0], "front": [0.754490315914154, -0.6563112735748291, -0.0], "behind": [-0.754490315914154, 0.6563112735748291, 0.0]}, "relationships": {"left": [[], [0], [0, 1], [0, 1, 2], [0, 1, 2, 3], [0, 1, 2, 3, 4], [0, 1, 2, 3, 4, 5], [0, 1, 2, 3, 4, 5, 6], [0, 1, 2, 3, 4, 5, 6, 7], [0, 1, 2, 3, 4, 5, 6, 7, 8], [0, 1, 2, 3, 4, 5, 6, 7, 8, 9], [0, 1, 2, 3, 4, 5, 6, 7, 8, 9, 10]], "front": [[1, 3, 4, 5, 6, 7, 8, 9, 10, 11], [5, 7, 9, 11], [1, 3, 5, 7, 8, 9, 10, 11], [9, 11], [1, 3, 5, 7, 9, 11], [9, 11], [1, 3, 5, 7, 9, 11], [], [1, 3, 5, 7, 9, 11], [], [1, 3, 5, 7, 9, 11], []], "behind": [[], [0, 2, 4, 6, 8, 10], [], [0, 2, 4, 6, 8, 10], [0], [0, 1, 2, 4, 6, 8, 10], [0], [0, 1, 2, 4, 6, 8, 10], [0, 2], [0, 1, 2, 3, 4, 5, 6, 8, 10], [0, 2], [0, 1, 2, 3, 4, 5, 6, 8, 10]], "right": [[1, 2, 3, 4, 5, 6, 7, 8, 9, 10, 11], [2, 3, 4, 5, 6, 7, 8, 9, 10, 11], [3, 4, 5, 6, 7, 8, 9, 10, 11], [4, 5, 6, 7, 8, 9, 10, 11], [5, 6, 7, 8, 9, 10, 11], [6, 7, 8, 9, 10, 11], [7, 8, 9, 10, 11], [8, 9, 10, 11], [9, 10, 11], [10, 11], [11], []]}}, {"objects": [{"color": "red", "size": "small", "rotation": 0.0, "pixel_coords": [174, 145, 11.133563995361328], "3d_coords": [-0.949999988079071, -1.0299999713897705, 0.3499999940395355], "material": "metal", "shape": "cube"}, {"color": "purple", "size": "small", "rotation": 0.0, "pixel_coords": [239, 181, 9.81330394744873], "3d_coords": [1.090000033378601, -0.9700000286102295, 0.3499999940395355], "material": "rubber", "shape": "sphere"}, {"color": "red", "size": "small", "rotation": 0.0, "pixel_coords": [311, 149, 10.938191413879395], "3d_coords": [1.1100000143051147, 1.0, 0.3499999940395355], "material": "metal", "shape": "cube"}, {"color": "purple", "size": "small", "rotation": 0.0, "pixel_coords": [382, 185, 9.658326148986816], "3d_coords": [2.950000047683716, 0.8999999761581421, 0.3499999940395355], "material": "rubber", "shape": "sphere"}], "image_filename": "CLEVR_shield-fovariant-13_000004.png", "split": "shield-fovariant-13", "image_index": 4, "directions": {"above": [0.0, 0.0, 1.0], "below": [-0.0, -0.0, -1.0], "right": [0.6563112735748291, 0.7544902563095093, -0.0], "left": [-0.6563112735748291, -0.7544902563095093, 0.0], "front": [0.754490315914154, -0.6563112735748291, -0.0], "behind": [-0.754490315914154, 0.6563112735748291, 0.0]}, "relationships": {"left": [[], [0], [0, 1], [0, 1, 2]], "front": [[1, 2, 3], [], [1, 3], []], "behind": [[], [0, 2], [0], [0, 2]], "right": [[1, 2, 3], [2, 3], [3], []]}}, {"objects": [{"color": "red", "size": "large", "rotation": 0.0, "pixel_coords": [106, 129, 10.990985870361328], "3d_coords": [-1.8899999856948853, -2.069999933242798, 0.699999988079071], "material": "metal", "shape": "cube"}, {"color": "purple", "size": "large", "rotation": 0.0, "pixel_coords": [159, 165, 9.624505043029785], "3d_coords": [0.15000000596046448, -2.0899999141693115, 0.699999988079071], "material": "rubber", "shape": "sphere"}, {"color": "red", "size": "large", "rotation": 0.0, "pixel_coords": [312, 134, 10.778788566589355], "3d_coords": [1.100000023841858, 1.0, 0.699999988079071], "material": "metal", "shape": "cube"}, {"color": "purple", "size": "large", "rotation": 0.0, "pixel_coords": [384, 169, 9.486504554748535], "3d_coords": [2.950000047683716, 0.8899999856948853, 0.699999988079071], "material": "rubber", "shape": "sphere"}], "image_filename": "CLEVR_shield-fovariant-13_000005.png", "split": "shield-fovariant-13", "image_index": 5, "directions": {"above": [0.0, 0.0, 1.0], "below": [-0.0, -0.0, -1.0], "right": [0.6563112735748291, 0.7544902563095093, -0.0], "left": [-0.6563112735748291, -0.7544902563095093, 0.0], "front": [0.754490315914154, -0.6563112735748291, -0.0], "behind": [-0.754490315914154, 0.6563112735748291, 0.0]}, "relationships": {"left": [[], [0], [0, 1], [0, 1, 2]], "front": [[1, 2, 3], [], [1, 3], []], "behind": [[], [0, 2], [0], [0, 2]], "right": [[1, 2, 3], [2, 3], [3], []]}}], "info": {"date": "05/30/2021", "version": "1.0", "split": "shield-fovariant-13", "license": "Creative Commons Attribution (CC-BY 4.0)"}}