{"info": "clevr groundtruth scene", "scenes": [{"image_index": 0, "image_filename": "CLEVR_val_000000.png", "objects": [{"shape": "sphere", "size": "large", "material": "metal", "color": "gray", "position": [0.05, 0.001, 0]}, {"shape": "cube", "size": "large", "material": "metal", "color": "gray", "position": [0.02, 1.935, 0]}]}, {"image_index": 1, "image_filename": "CLEVR_val_000001.png", "objects": [{"shape": "cube", "size": "large", "material": "metal", "color": "gray", "position": [0.092, -1.996, 0]}, {"shape": "cube", "size": "large", "material": "metal", "color": "cyan", "position": [0.069, 0.027, 0]}, {"shape": "sphere", "size": "large", "material": "metal", "color": "gray", "position": [0.066, 1.979, 0]}]}, {"image_index": 2, "image_filename": "CLEVR_val_000002.png", "objects": [{"shape": "sphere", "size": "large", "material": "metal", "color": "gray", "position": [0.006, -1.984, 0]}, {"shape": "cube", "size": "large", "material": "metal", "color": "gray", "position": [-0.069, -0.021, 0]}, {"shape": "sphere", "size": "large", "material": "metal", "color": "cyan", "position": [-0.079, 1.959, 0]}]}, {"image_index": 3, "image_filename": "CLEVR_val_000003.png", "objects": [{"shape": "sphere", "size": "small", "material": "metal", "color": "purple", "position": [-0.02, -2.096, 0]}, {"shape": "cube", "size": "small", "material": "metal", "color": "purple", "position": [-0.093, -1.125, 0]}, {"shape": "sphere", "size": "small", "material": "metal", "color": "purple", "position": [-0.097, -0.078, 0]}, {"shape": "sphere", "size": "small", "material": "metal", "color": "purple", "position": [-0.063, 0.928, 0]}]}, {"image_index": 4, "image_filename": "CLEVR_val_000004.png", "objects": [{"shape": "cylinder", "size": "large", "material": "metal", "color": "gray", "position": [0.044, -2.347, 0]}, {"shape": "sphere", "size": "large", "material": "metal", "color": "yellow", "position": [0.11, -1.053, 0]}, {"shape": "cube", "size": "large", "material": "metal", "color": "yellow", "position": [0.045, 0.968, 0]}, {"shape": "sphere", "size": "large", "material": "metal", "color": "yellow", "position": [0.123, 2.225, 0]}]}, {"image_index": 5, "image_filename": "CLEVR_val_000005.png", "objects": [{"shape": "sphere", "size": "large", "material": "metal", "color": "brown", "position": [0.031, -2.024, 0]}, {"shape": "cube", "size": "large", "material": "metal", "color": "brown", "position": [0.068, -0.065, 0]}, {"shape": "cylinder", "size": "large", "material": "metal", "color": "cyan", "position": [0.041, 1.996, 0]}]}]}