{"info": "clevr groundtruth scene", "scenes": [{"image_index": 0, "image_filename": "CLEVR_val_000000.png", "objects": [{"shape": "cylinder", "size": "small", "material": "metal", "color": "brown", "position": [0.03, -2.04, 0]}, {"shape": "sphere", "size": "small", "material": "metal", "color": "brown", "position": [0.055, -1.035, 0]}, {"shape": "cylinder", "size": "small", "material": "metal", "color": "brown", "position": [0.025, -0.088, 0]}]}, {"image_index": 1, "image_filename": "CLEVR_val_000001.png", "objects": [{"shape": "sphere", "size": "small", "material": "metal", "color": "brown", "position": [-0.109, -2.097, 0]}, {"shape": "cylinder", "size": "small", "material": "metal", "color": "brown", "position": [-0.135, -0.119, 0]}, {"shape": "sphere", "size": "small", "material": "metal", "color": "brown", "position": [-0.113, 0.886, 0]}, {"shape": "cylinder", "size": "small", "material": "metal", "color": "brown", "position": [-0.073, 1.871, 0]}]}, {"image_index": 2, "image_filename": "CLEVR_val_000002.png", "objects": [{"shape": "cylinder", "size": "small", "material": "metal", "color": "brown", "position": [0.099, -1.942, 0]}, {"shape": "cylinder", "size": "small", "material": "metal", "color": "brown", "position": [0.077, -0.936, 0]}, {"shape": "sphere", "size": "small", "material": "metal", "color": "brown", "position": [0.044, 0.139, 0]}]}, {"image_index": 3, "image_filename": "CLEVR_val_000003.png", "objects": [{"shape": "cylinder", "size": "large", "material": "metal", "color": "gray", "position": [-0.045, -2.599, 0]}, {"shape": "sphere", "size": "large", "material": "metal", "color": "brown", "position": [0.045, -0.609, 0]}, {"shape": "cylinder", "size": "large", "material": "metal", "color": "yellow", "position": [-0.025, 1.484, 0]}]}, {"image_index": 4, "image_filename": "CLEVR_val_000004.png", "objects": [{"shape": "cylinder", "size": "large", "material": "metal", "color": "brown", "position": [0.141, -1.4, 0]}, {"shape": "sphere", "size": "small", "material": "metal", "color": "brown", "position": [0.084, 0.579, 0]}, {"shape": "cylinder", "size": "small", "material": "rubber", "color": "brown", "position": [0.117, 2.595, 0]}]}, {"image_index": 5, "image_filename": "CLEVR_val_000005.png", "objects": [{"shape": "cube", "size": "small", "material": "metal", "color": "yellow", "position": [-0.108, -2.399, 0]}, {"shape": "cube", "size": "small", "material": "metal", "color": "gray", "position": [-0.104, -1.441, 0]}, {"shape": "cylinder", "size": "small", "material": "rubber", "color": "brown", "position": [-0.127, -0.361, 0]}, {"shape": "sphere", "size": "large", "material": "metal", "color": "gray", "position": [-0.081, 0.812, 0]}, {"shape": "cylinder", "size": "small", "material": "rubber", "color": "yellow", "position": [-0.096, 2.1, 0]}]}]}