{
  "split": "partition-fovariant-16",
  "image_filename": "CLEVR_partition-fovariant-16_000005.png",
  "image_index": 5,
  "relationships": {
    "behind": [
      [],
      [],
      [
        0
      ]
    ],
    "left": [
      [],
      [
        0
      ],
      [
        0,
        1
      ]
    ],
    "front": [
      [
        2
      ],
      [],
      []
    ],
    "right": [
      [
        1,
        2
      ],
      [
        2
      ],
      []
    ]
  },
  "directions": {
    "left": [
      -0.6563112735748291,
      -0.7544902563095093,
      0.0
    ],
    "behind": [
      -0.754490315914154,
      0.6563112735748291,
      0.0
    ],
    "below": [
      -0.0,
      -0.0,
      -1.0
    ],
    "front": [
      0.754490315914154,
      -0.6563112735748291,
      -0.0
    ],
    "right": [
      0.6563112735748291,
      0.7544902563095093,
      -0.0
    ],
    "above": [
      0.0,
      0.0,
      1.0
    ]
  },
  "objects": [
    {
      "3d_coords": [
        -1.940000057220459,
        -2.119999885559082,
        0.699999988079071
      ],
      "color": "cyan",
      "pixel_coords": [
        103,
        129,
        10.995306968688965
      ],
      "material": "metal",
      "shape": "sphere",
      "rotation": 0.0,
      "size": "large"
    },
    {
      "3d_coords": [
        -0.5199999809265137,
        -0.5799999833106995,
        0.3499999940395355
      ],
      "color": "cyan",
      "pixel_coords": [
        203,
        145,
        11.107955932617188
      ],
      "material": "metal",
      "shape": "sphere",
      "rotation": 0.0,
      "size": "small"
    },
    {
      "3d_coords": [
        0.9200000166893005,
        0.8500000238418579,
        0.699999988079071
      ],
      "color": "cyan",
      "pixel_coords": [
        300,
        133,
        10.811677932739258
      ],
      "material": "metal",
      "shape": "cube",
      "rotation": 0.0,
      "size": "large"
    }
  ]
}