{
  "split": "alternation-fovariant-18",
  "relationships": {
    "left": [
      [],
      [
        0
      ]
    ],
    "behind": [
      [],
      []
    ],
    "right": [
      [
        1
      ],
      []
    ],
    "front": [
      [],
      []
    ]
  },
  "image_filename": "CLEVR_alternation-fovariant-18_000002.png",
  "objects": [
    {
      "3d_coords": [
        -2.0799999237060547,
        -2.069999933242798,
        0.699999988079071
      ],
      "shape": "cylinder",
      "material": "metal",
      "color": "cyan",
      "size": "large",
      "rotation": 0.0,
      "pixel_coords": [
        102,
        126,
        11.117179870605469
      ]
    },
    {
      "3d_coords": [
        -0.1599999964237213,
        -0.09000000357627869,
        0.699999988079071
      ],
      "shape": "cube",
      "material": "metal",
      "color": "yellow",
      "size": "large",
      "rotation": 0.0,
      "pixel_coords": [
        232,
        129,
        10.985904693603516
      ]
    }
  ],
  "image_index": 2,
  "directions": {
    "behind": [
      -0.754490315914154,
      0.6563112735748291,
      0.0
    ],
    "below": [
      -0.0,
      -0.0,
      -1.0
    ],
    "front": [
      0.754490315914154,
      -0.6563112735748291,
      -0.0
    ],
    "left": [
      -0.6563112735748291,
      -0.7544902563095093,
      0.0
    ],
    "above": [
      0.0,
      0.0,
      1.0
    ],
    "right": [
      0.6563112735748291,
      0.7544902563095093,
      -0.0
    ]
  }
}