{
  "image_index": 4,
  "image_filename": "CLEVR_breaking-fovariant-4_000004.png",
  "relationships": {
    "right": [
      [
        1,
        2
      ],
      [
        2
      ],
      []
    ],
    "left": [
      [],
      [
        0
      ],
      [
        0,
        1
      ]
    ],
    "front": [
      [
        2
      ],
      [
        2
      ],
      []
    ],
    "behind": [
      [],
      [],
      [
        0,
        1
      ]
    ]
  },
  "split": "breaking-fovariant-4",
  "objects": [
    {
      "pixel_coords": [
        115,
        129,
        10.998811721801758
      ],
      "color": "yellow",
      "3d_coords": [
        -1.7799999713897705,
        -1.9299999475479126,
        0.699999988079071
      ],
      "material": "metal",
      "rotation": 0.0,
      "size": "large",
      "shape": "cube"
    },
    {
      "pixel_coords": [
        249,
        133,
        10.839241027832031
      ],
      "color": "cyan",
      "3d_coords": [
        0.20000000298023224,
        0.07000000029802322,
        0.699999988079071
      ],
      "material": "metal",
      "rotation": 0.0,
      "size": "large",
      "shape": "sphere"
    },
    {
      "pixel_coords": [
        387,
        137,
        10.642412185668945
      ],
      "color": "yellow",
      "3d_coords": [
        2.2100000381469727,
        2.0399999618530273,
        0.699999988079071
      ],
      "material": "metal",
      "rotation": 0.0,
      "size": "large",
      "shape": "cube"
    }
  ],
  "directions": {
    "left": [
      -0.6563112735748291,
      -0.7544902563095093,
      0.0
    ],
    "front": [
      0.754490315914154,
      -0.6563112735748291,
      -0.0
    ],
    "above": [
      0.0,
      0.0,
      1.0
    ],
    "behind": [
      -0.754490315914154,
      0.6563112735748291,
      0.0
    ],
    "below": [
      -0.0,
      -0.0,
      -1.0
    ],
    "right": [
      0.6563112735748291,
      0.7544902563095093,
      -0.0
    ]
  }
}