{"info": "clevr groundtruth scene", "scenes": [{"image_index": 0, "image_filename": "CLEVR_val_000000.png", "objects": [{"shape": "sphere", "size": "large", "material": "metal", "color": "purple", "position": [0.064, -2.075, 0]}, {"shape": "cube", "size": "small", "material": "rubber", "color": "cyan", "position": [0.037, -0.027, 0]}, {"shape": "sphere", "size": "large", "material": "metal", "color": "purple", "position": [0.049, 1.915, 0]}]}, {"image_index": 1, "image_filename": "CLEVR_val_000001.png", "objects": [{"shape": "sphere", "size": "large", "material": "metal", "color": "purple", "position": [-0.047, -2.254, 0]}, {"shape": "cube", "size": "small", "material": "metal", "color": "cyan", "position": [-0.032, -0.988, 0]}, {"shape": "sphere", "size": "large", "material": "metal", "color": "purple", "position": [-0.021, 0.923, 0]}, {"shape": "cube", "size": "small", "material": "metal", "color": "cyan", "position": [-0.024, 2.186, 0]}]}, {"image_index": 2, "image_filename": "CLEVR_val_000002.png", "objects": [{"shape": "sphere", "size": "large", "material": "metal", "color": "purple", "position": [-0.085, -0.052, 0]}, {"shape": "cube", "size": "small", "material": "metal", "color": "purple", "position": [-0.049, 1.543, 0]}]}, {"image_index": 3, "image_filename": "CLEVR_val_000003.png", "objects": [{"shape": "cube", "size": "small", "material": "metal", "color": "brown", "position": [0.062, -1.016, 0]}, {"shape": "sphere", "size": "large", "material": "metal", "color": "purple", "position": [0.006, 0.506, 0]}]}, {"image_index": 4, "image_filename": "CLEVR_val_000004.png", "objects": [{"shape": "sphere", "size": "large", "material": "metal", "color": "purple", "position": [0.009, -2.393, 0]}, {"shape": "sphere", "size": "large", "material": "metal", "color": "purple", "position": [0.055, -0.37, 0]}, {"shape": "cube", "size": "small", "material": "metal", "color": "cyan", "position": [0.044, 1.094, 0]}, {"shape": "sphere", "size": "large", "material": "metal", "color": "purple", "position": [0.05, 2.297, 0]}]}, {"image_index": 5, "image_filename": "CLEVR_val_000005.png", "objects": [{"shape": "sphere", "size": "large", "material": "metal", "color": "purple", "position": [-0.075, -2.039, 0]}, {"shape": "cube", "size": "small", "material": "metal", "color": "cyan", "position": [-0.078, -0.09, 0]}, {"shape": "sphere", "size": "large", "material": "metal", "color": "blue", "position": [0.013, 1.976, 0]}]}]}